spark3d_batch-0.1.7.dist-info/licenses/LICENSE
spark3dbatch/__init__.py
spark3dbatch/batch_spark3d.py
spark3dbatch/helper.py
spark3dbatch/log_manager.py
spark3dbatch/spark3d.py
spark3dbatch/xml_parser.py
"spark3dbatch/data/Coax_filter_CST(M, C, Eigenmode).xml"
spark3dbatch/data/__init__.py
spark3d_batch-0.1.7.dist-info/METADATA
spark3d_batch-0.1.7.dist-info/WHEEL
spark3d_batch-0.1.7.dist-info/top_level.txt
spark3d_batch-0.1.7.dist-info/RECORD
