Metadata-Version: 2.4
Name: spark3d-batch
Version: 0.1.7
Summary: Launch SPARK3D simulations by batch; list of powers or accelerating fields.
Author-email: Adrien Plaçais <placais@lpsc.in2p3.fr>
Project-URL: Homepage, https://github.com/AdrienPlacais/Spark3DBatch
Project-URL: documentation, https://spark3dbatch.readthedocs.io/en/latest/
Keywords: post treatment,multipactor
Classifier: Development Status :: 3 - Alpha
Classifier: Intended Audience :: Science/Research
Classifier: License :: OSI Approved :: MIT License
Classifier: Operating System :: OS Independent
Classifier: Programming Language :: Python :: 3.9
Classifier: Topic :: Scientific/Engineering :: Physics
Requires-Python: >=3.9
License-File: LICENSE
Requires-Dist: numpy<3,>=2
Requires-Dist: pre-commit<5,>=4
Requires-Dist: pandas<3,>=2.2
Provides-Extra: docs
Requires-Dist: myst-parser<5,>=4; extra == "docs"
Requires-Dist: nbsphinx<1,>=0.9.6; extra == "docs"
Requires-Dist: sphinx-autodoc-typehints<4,>=3.0.1; extra == "docs"
Requires-Dist: sphinx-rtd-theme<4,>=3; extra == "docs"
Requires-Dist: sphinx-tabs<4,>=3.4; extra == "docs"
Requires-Dist: sphinxcontrib-bibtex<3,>=2.6; extra == "docs"
Dynamic: license-file
